{
    "blocks": [
        {
            "type": "section",
            "text": {
                "type": "mrkdwn",
                "text": "TITLE_MESSAGE"
            }
        },
        {
            "type": "divider"
        },
        {
            "type": "context",
            "elements": [
                {
                    "type": "mrkdwn",
                    "text": "NAME_OF_PULL_REQUEST"
                }
            ]
        },
        {
            "type": "context",
            "elements": [
                {
                    "type": "mrkdwn",
                    "text": "AUTHOR"
                }
            ]
        },
        {
            "type": "context",
            "elements": [
                {
                    "type": "mrkdwn",
                    "text": "REVIEWERS_LIST"
                }
            ]
        },
        {
            "type": "context",
            "elements": [
                {
                    "type": "mrkdwn",
                    "text": "DATE"
                }
            ]
        }
    ]
}